{
  "_meta": {
    "source": "Wizard of Odds Appendix 1 - Infinite Deck",
    "rules": "S17, DAS, Late Surrender",
    "url": "https://wizardofodds.com/games/blackjack/appendix/1/",
    "extracted": "2026-06-15",
    "note": "Infinite deck approximation. For composition-dependent values see Appendix 9."
  },
  "hard": {
    "4": { "2": {"Hit":-0.1149,"Stand":-0.2928,"Double":-0.5856}, "3": {"Hit":-0.0826,"Stand":-0.2523,"Double":-0.5045}, "4": {"Hit":-0.0494,"Stand":-0.2111,"Double":-0.4221}, "5": {"Hit":-0.0124,"Stand":-0.1672,"Double":-0.3344}, "6": {"Hit":0.0111,"Stand":-0.1537,"Double":-0.3074}, "7": {"Hit":-0.0883,"Stand":-0.4754,"Double":-0.9508}, "8": {"Hit":-0.1593,"Stand":-0.5105,"Double":-1.0210}, "9": {"Hit":-0.2407,"Stand":-0.5432,"Double":-1.0863}, "10": {"Hit":-0.2892,"Stand":-0.5404,"Double":-1.0809}, "A": {"Hit":-0.2531,"Stand":-0.6670,"Double":-1.3339} },
    "5": { "2": {"Hit":-0.1282,"Stand":-0.2928,"Double":-0.5856}, "3": {"Hit":-0.0953,"Stand":-0.2523,"Double":-0.5045}, "4": {"Hit":-0.0615,"Stand":-0.2111,"Double":-0.4221}, "5": {"Hit":-0.0240,"Stand":-0.1672,"Double":-0.3344}, "6": {"Hit":-0.0012,"Stand":-0.1537,"Double":-0.3074}, "7": {"Hit":-0.1194,"Stand":-0.4754,"Double":-0.9508}, "8": {"Hit":-0.1881,"Stand":-0.5105,"Double":-1.0210}, "9": {"Hit":-0.2666,"Stand":-0.5432,"Double":-1.0863}, "10": {"Hit":-0.3134,"Stand":-0.5404,"Double":-1.0809}, "A": {"Hit":-0.2786,"Stand":-0.6670,"Double":-1.3339} },
    "6": { "2": {"Hit":-0.1408,"Stand":-0.2928,"Double":-0.5641}, "3": {"Hit":-0.1073,"Stand":-0.2523,"Double":-0.4837}, "4": {"Hit":-0.0729,"Stand":-0.2111,"Double":-0.4021}, "5": {"Hit":-0.0349,"Stand":-0.1672,"Double":-0.3156}, "6": {"Hit":-0.0130,"Stand":-0.1537,"Double":-0.2819}, "7": {"Hit":-0.1519,"Stand":-0.4754,"Double":-0.8940}, "8": {"Hit":-0.2172,"Stand":-0.5105,"Double":-1.0013}, "9": {"Hit":-0.2926,"Stand":-0.5432,"Double":-1.0678}, "10": {"Hit":-0.3377,"Stand":-0.5404,"Double":-1.0623}, "A": {"Hit":-0.3041,"Stand":-0.6670,"Double":-1.3048} },
    "7": { "2": {"Hit":-0.1092,"Stand":-0.2928,"Double":-0.4358}, "3": {"Hit":-0.0766,"Stand":-0.2523,"Double":-0.3598}, "4": {"Hit":-0.0430,"Stand":-0.2111,"Double":-0.2823}, "5": {"Hit":-0.0073,"Stand":-0.1672,"Double":-0.2027}, "6": {"Hit":0.0292,"Stand":-0.1537,"Double":-0.1383}, "7": {"Hit":-0.0688,"Stand":-0.4754,"Double":-0.5893}, "8": {"Hit":-0.2106,"Stand":-0.5105,"Double":-0.8471}, "9": {"Hit":-0.2854,"Stand":-0.5432,"Double":-0.9571}, "10": {"Hit":-0.3191,"Stand":-0.5404,"Double":-0.9509}, "A": {"Hit":-0.3101,"Stand":-0.6670,"Double":-1.1305} },
    "8": { "2": {"Hit":-0.0218,"Stand":-0.2928,"Double":-0.2045}, "3": {"Hit":0.0080,"Stand":-0.2523,"Double":-0.1362}, "4": {"Hit":0.0388,"Stand":-0.2111,"Double":-0.0664}, "5": {"Hit":0.0708,"Stand":-0.1672,"Double":0.0035}, "6": {"Hit":0.1150,"Stand":-0.1537,"Double":0.0870}, "7": {"Hit":0.0822,"Stand":-0.4754,"Double":-0.1877}, "8": {"Hit":-0.0599,"Stand":-0.5105,"Double":-0.4520}, "9": {"Hit":-0.2102,"Stand":-0.5432,"Double":-0.7185}, "10": {"Hit":-0.2494,"Stand":-0.5404,"Double":-0.7466}, "A": {"Hit":-0.1970,"Stand":-0.6670,"Double":-0.8107} },
    "9": { "2": {"Hit":0.0744,"Stand":-0.2928,"Double":0.0611}, "3": {"Hit":0.1013,"Stand":-0.2523,"Double":0.1208}, "4": {"Hit":0.1290,"Stand":-0.2111,"Double":0.1819}, "5": {"Hit":0.1580,"Stand":-0.1672,"Double":0.2431}, "6": {"Hit":0.1960,"Stand":-0.1537,"Double":0.3171}, "7": {"Hit":0.1719,"Stand":-0.4754,"Double":0.1043}, "8": {"Hit":0.0984,"Stand":-0.5105,"Double":-0.0264}, "9": {"Hit":-0.0522,"Stand":-0.5432,"Double":-0.3010}, "10": {"Hit":-0.1530,"Stand":-0.5404,"Double":-0.4667}, "A": {"Hit":-0.0657,"Stand":-0.6670,"Double":-0.4329} },
    "10": { "2": {"Hit":0.1825,"Stand":-0.2928,"Double":0.3589}, "3": {"Hit":0.2061,"Stand":-0.2523,"Double":0.4093}, "4": {"Hit":0.2305,"Stand":-0.2111,"Double":0.4609}, "5": {"Hit":0.2563,"Stand":-0.1672,"Double":0.5125}, "6": {"Hit":0.2878,"Stand":-0.1537,"Double":0.5756}, "7": {"Hit":0.2569,"Stand":-0.4754,"Double":0.3924}, "8": {"Hit":0.1980,"Stand":-0.5105,"Double":0.2866}, "9": {"Hit":0.1165,"Stand":-0.5432,"Double":0.1443}, "10": {"Hit":0.0253,"Stand":-0.5404,"Double":-0.0087}, "A": {"Hit":0.0815,"Stand":-0.6670,"Double":-0.0140} },
    "11": { "2": {"Hit":0.2384,"Stand":-0.2928,"Double":0.4706}, "3": {"Hit":0.2603,"Stand":-0.2523,"Double":0.5178}, "4": {"Hit":0.2830,"Stand":-0.2111,"Double":0.5660}, "5": {"Hit":0.3074,"Stand":-0.1672,"Double":0.6147}, "6": {"Hit":0.3337,"Stand":-0.1537,"Double":0.6674}, "7": {"Hit":0.2921,"Stand":-0.4754,"Double":0.4629}, "8": {"Hit":0.2300,"Stand":-0.5105,"Double":0.3507}, "9": {"Hit":0.1583,"Stand":-0.5432,"Double":0.2278}, "10": {"Hit":0.1195,"Stand":-0.5404,"Double":0.1797}, "A": {"Hit":0.1430,"Stand":-0.6670,"Double":0.1091} },
    "12": { "2": {"Hit":-0.2534,"Stand":-0.2928,"Double":-0.5068}, "3": {"Hit":-0.2337,"Stand":-0.2523,"Double":-0.4674}, "4": {"Hit":-0.2135,"Stand":-0.2111,"Double":-0.4271}, "5": {"Hit":-0.1933,"Stand":-0.1672,"Double":-0.3865}, "6": {"Hit":-0.1705,"Stand":-0.1537,"Double":-0.3411}, "7": {"Hit":-0.2128,"Stand":-0.4754,"Double":-0.5067}, "8": {"Hit":-0.2716,"Stand":-0.5105,"Double":-0.6157}, "9": {"Hit":-0.3400,"Stand":-0.5432,"Double":-0.7375}, "10": {"Hit":-0.3810,"Stand":-0.5404,"Double":-0.7968}, "A": {"Hit":-0.3505,"Stand":-0.6670,"Double":-0.8293} },
    "13": { "2": {"Hit":-0.3078,"Stand":-0.2928,"Double":-0.6156}, "3": {"Hit":-0.2912,"Stand":-0.2523,"Double":-0.5824}, "4": {"Hit":-0.2742,"Stand":-0.2111,"Double":-0.5484}, "5": {"Hit":-0.2573,"Stand":-0.1672,"Double":-0.5147}, "6": {"Hit":-0.2356,"Stand":-0.1537,"Double":-0.4713}, "7": {"Hit":-0.2691,"Stand":-0.4754,"Double":-0.5874}, "8": {"Hit":-0.3236,"Stand":-0.5105,"Double":-0.6910}, "9": {"Hit":-0.3872,"Stand":-0.5432,"Double":-0.8078}, "10": {"Hit":-0.4253,"Stand":-0.5404,"Double":-0.8675}, "A": {"Hit":-0.3969,"Stand":-0.6670,"Double":-0.8806} },
    "14": { "2": {"Hit":-0.3622,"Stand":-0.2928,"Double":-0.7244}, "3": {"Hit":-0.3487,"Stand":-0.2523,"Double":-0.6975}, "4": {"Hit":-0.3349,"Stand":-0.2111,"Double":-0.6698}, "5": {"Hit":-0.3214,"Stand":-0.1672,"Double":-0.6428}, "6": {"Hit":-0.3007,"Stand":-0.1537,"Double":-0.6015}, "7": {"Hit":-0.3213,"Stand":-0.4754,"Double":-0.6681}, "8": {"Hit":-0.3719,"Stand":-0.5105,"Double":-0.7663}, "9": {"Hit":-0.4309,"Stand":-0.5432,"Double":-0.8781}, "10": {"Hit":-0.4663,"Stand":-0.5404,"Double":-0.9382}, "A": {"Hit":-0.4400,"Stand":-0.6670,"Double":-0.9318} },
    "15": { "2": {"Hit":-0.4166,"Stand":-0.2928,"Double":-0.8332}, "3": {"Hit":-0.4062,"Stand":-0.2523,"Double":-0.8125}, "4": {"Hit":-0.3956,"Stand":-0.2111,"Double":-0.7912}, "5": {"Hit":-0.3855,"Stand":-0.1672,"Double":-0.7709}, "6": {"Hit":-0.3658,"Stand":-0.1537,"Double":-0.7317}, "7": {"Hit":-0.3698,"Stand":-0.4754,"Double":-0.7488}, "8": {"Hit":-0.4168,"Stand":-0.5105,"Double":-0.8416}, "9": {"Hit":-0.4716,"Stand":-0.5432,"Double":-0.9484}, "10": {"Hit":-0.5044,"Stand":-0.5404,"Double":-1.0090}, "A": {"Hit":-0.4800,"Stand":-0.6670,"Double":-0.9831} },
    "16": { "2": {"Hit":-0.4710,"Stand":-0.2928,"Double":-0.9420}, "3": {"Hit":-0.4638,"Stand":-0.2523,"Double":-0.9275}, "4": {"Hit":-0.4563,"Stand":-0.2111,"Double":-0.9126}, "5": {"Hit":-0.4495,"Stand":-0.1672,"Double":-0.8990}, "6": {"Hit":-0.4309,"Stand":-0.1537,"Double":-0.8619}, "7": {"Hit":-0.4148,"Stand":-0.4754,"Double":-0.8296}, "8": {"Hit":-0.4584,"Stand":-0.5105,"Double":-0.9169}, "9": {"Hit":-0.5093,"Stand":-0.5432,"Double":-1.0186}, "10": {"Hit":-0.5398,"Stand":-0.5404,"Double":-1.0797}, "A": {"Hit":-0.5171,"Stand":-0.6670,"Double":-1.0343} },
    "17": { "2": {"Hit":-0.5362,"Stand":-0.1530}, "3": {"Hit":-0.5317,"Stand":-0.1172}, "4": {"Hit":-0.5270,"Stand":-0.0806}, "5": {"Hit":-0.5230,"Stand":-0.0449}, "6": {"Hit":-0.5088,"Stand":0.0117}, "7": {"Hit":-0.4835,"Stand":-0.1068}, "8": {"Hit":-0.5060,"Stand":-0.3820}, "9": {"Hit":-0.5537,"Stand":-0.4232}, "10": {"Hit":-0.5845,"Stand":-0.4197}, "A": {"Hit":-0.5573,"Stand":-0.4780} },
    "18": { "2": {"Hit":-0.6224,"Stand":0.1217}, "3": {"Hit":-0.6200,"Stand":0.1483}, "4": {"Hit":-0.6175,"Stand":0.1759}, "5": {"Hit":-0.6153,"Stand":0.1996}, "6": {"Hit":-0.6075,"Stand":0.2834}, "7": {"Hit":-0.5911,"Stand":0.3996}, "8": {"Hit":-0.5911,"Stand":0.1060}, "9": {"Hit":-0.6165,"Stand":-0.1832}, "10": {"Hit":-0.6477,"Stand":-0.1783}, "A": {"Hit":-0.6265,"Stand":-0.1002} },
    "19": { "2": {"Hit":-0.7291,"Stand":0.3863}, "3": {"Hit":-0.7280,"Stand":0.4044}, "4": {"Hit":-0.7269,"Stand":0.4232}, "5": {"Hit":-0.7260,"Stand":0.4395}, "6": {"Hit":-0.7226,"Stand":0.4960}, "7": {"Hit":-0.7155,"Stand":0.6160}, "8": {"Hit":-0.7137,"Stand":0.5939}, "9": {"Hit":-0.7156,"Stand":0.2876}, "10": {"Hit":-0.7294,"Stand":0.0631}, "A": {"Hit":-0.7248,"Stand":0.2776} },
    "20": { "2": {"Hit":-0.8552,"Stand":0.6400}, "3": {"Hit":-0.8550,"Stand":0.6503}, "4": {"Hit":-0.8547,"Stand":0.6611}, "5": {"Hit":-0.8545,"Stand":0.6704}, "6": {"Hit":-0.8536,"Stand":0.7040}, "7": {"Hit":-0.8519,"Stand":0.7732}, "8": {"Hit":-0.8515,"Stand":0.7918}, "9": {"Hit":-0.8508,"Stand":0.7584}, "10": {"Hit":-0.8490,"Stand":0.5545}, "A": {"Hit":-0.8521,"Stand":0.6555} },
    "21": { "2": {"Hit":-0.8820,"Stand":0.8820}, "3": {"Hit":-0.8853,"Stand":0.8853}, "4": {"Hit":-0.8888,"Stand":0.8888}, "5": {"Hit":-0.8918,"Stand":0.8918}, "6": {"Hit":-0.9028,"Stand":0.9028}, "7": {"Hit":-0.9259,"Stand":0.9259}, "8": {"Hit":-0.9306,"Stand":0.9306}, "9": {"Hit":-0.9392,"Stand":0.9392}, "10": {"Hit":-0.9626,"Stand":0.9626}, "A": {"Hit":-0.9222,"Stand":0.9222} }
  },
  "soft": {
    "12": { "2": {"Hit":0.0818,"Double":-0.0716}, "3": {"Hit":0.1035,"Double":-0.0072}, "4": {"Hit":0.1266,"Double":0.0584}, "5": {"Hit":0.1565,"Double":0.1260}, "6": {"Hit":0.1860,"Double":0.1797}, "7": {"Hit":0.1655,"Double":-0.1839}, "8": {"Hit":0.0951,"Double":-0.3144}, "9": {"Hit":0.0001,"Double":-0.4564}, "10": {"Hit":-0.0700,"Double":-0.5140}, "A": {"Hit":-0.0205,"Double":-0.6244} },
    "13": { "2": {"Hit":0.0466,"Double":-0.0716}, "3": {"Hit":0.0741,"Double":-0.0072}, "4": {"Hit":0.1025,"Double":0.0584}, "5": {"Hit":0.1334,"Double":0.1260}, "6": {"Hit":0.1617,"Double":0.1797}, "7": {"Hit":0.1224,"Double":-0.1839}, "8": {"Hit":0.0541,"Double":-0.3144}, "9": {"Hit":-0.0377,"Double":-0.4564}, "10": {"Hit":-0.1049,"Double":-0.5140}, "A": {"Hit":-0.0573,"Double":-0.6244} },
    "14": { "2": {"Hit":0.0224,"Double":-0.0716}, "3": {"Hit":0.0508,"Double":-0.0072}, "4": {"Hit":0.0801,"Double":0.0584}, "5": {"Hit":0.1119,"Double":0.1260}, "6": {"Hit":0.1392,"Double":0.1797}, "7": {"Hit":0.0795,"Double":-0.1839}, "8": {"Hit":0.0133,"Double":-0.3144}, "9": {"Hit":-0.0752,"Double":-0.4564}, "10": {"Hit":-0.1395,"Double":-0.5140}, "A": {"Hit":-0.0939,"Double":-0.6244} },
    "15": { "2": {"Hit":-0.0001,"Double":-0.0716}, "3": {"Hit":0.0292,"Double":-0.0072}, "4": {"Hit":0.0593,"Double":0.0584}, "5": {"Hit":0.0920,"Double":0.1260}, "6": {"Hit":0.1182,"Double":0.1797}, "7": {"Hit":0.0370,"Double":-0.1839}, "8": {"Hit":-0.0271,"Double":-0.3144}, "9": {"Hit":-0.1122,"Double":-0.4564}, "10": {"Hit":-0.1737,"Double":-0.5140}, "A": {"Hit":-0.1300,"Double":-0.6244} },
    "16": { "2": {"Hit":-0.0210,"Double":-0.0716}, "3": {"Hit":0.0091,"Double":-0.0072}, "4": {"Hit":0.0400,"Double":0.0584}, "5": {"Hit":0.0734,"Double":0.1260}, "6": {"Hit":0.0988,"Double":0.1797}, "7": {"Hit":-0.0049,"Double":-0.1839}, "8": {"Hit":-0.0668,"Double":-0.3144}, "9": {"Hit":-0.1486,"Double":-0.4564}, "10": {"Hit":-0.2074,"Double":-0.5140}, "A": {"Hit":-0.1656,"Double":-0.6244} },
    "17": { "2": {"Hit":-0.0005,"Double":-0.0070}, "3": {"Hit":0.0290,"Double":0.0551}, "4": {"Hit":0.0593,"Double":0.1187}, "5": {"Hit":0.0912,"Double":0.1824}, "6": {"Hit":0.1281,"Double":0.2561}, "7": {"Hit":0.0538,"Double":-0.0138}, "8": {"Hit":-0.0729,"Double":-0.2551}, "9": {"Hit":-0.1498,"Double":-0.4010}, "10": {"Hit":-0.1969,"Double":-0.4583}, "A": {"Hit":-0.1796,"Double":-0.5372} },
    "18": { "2": {"Hit":0.0629,"Double":0.1198}, "3": {"Hit":0.0902,"Double":0.1776}, "4": {"Hit":0.1185,"Double":0.2370}, "5": {"Hit":0.1476,"Double":0.2952}, "6": {"Hit":0.1908,"Double":0.3815}, "7": {"Hit":0.1707,"Double":0.2199}, "8": {"Hit":0.0397,"Double":-0.0299}, "9": {"Hit":-0.1007,"Double":-0.2902}, "10": {"Hit":-0.1438,"Double":-0.3469}, "A": {"Hit":-0.0929,"Double":-0.3628} },
    "19": { "2": {"Hit":0.1240,"Double":0.2419}, "3": {"Hit":0.1493,"Double":0.2958}, "4": {"Hit":0.1756,"Double":0.3512}, "5": {"Hit":0.2030,"Double":0.4060}, "6": {"Hit":0.2398,"Double":0.4796}, "7": {"Hit":0.2206,"Double":0.3198}, "8": {"Hit":0.1523,"Double":0.1953}, "9": {"Hit":0.0079,"Double":-0.0729}, "10": {"Hit":-0.0881,"Double":-0.2355}, "A": {"Hit":-0.0057,"Double":-0.1884} },
    "20": { "2": {"Hit":0.1825,"Double":0.3589}, "3": {"Hit":0.2061,"Double":0.4093}, "4": {"Hit":0.2305,"Double":0.4609}, "5": {"Hit":0.2563,"Double":0.5125}, "6": {"Hit":0.2878,"Double":0.5756}, "7": {"Hit":0.2569,"Double":0.3924}, "8": {"Hit":0.1980,"Double":0.2866}, "9": {"Hit":0.1165,"Double":0.1443}, "10": {"Hit":0.0253,"Double":-0.0087}, "A": {"Hit":0.0815,"Double":-0.0140} }
  },
  "pair": {
    "2,2": { "2": {"Split":-0.0843}, "3": {"Split":-0.0157}, "4": {"Split":0.0591}, "5": {"Split":0.1517}, "6": {"Split":0.2269}, "7": {"Split":0.0067}, "8": {"Split":-0.1767}, "9": {"Split":-0.3869}, "10": {"Split":-0.5072}, "A": {"Split":-0.4336} },
    "3,3": { "2": {"Split":-0.1377}, "3": {"Split":-0.0563}, "4": {"Split":0.0299}, "5": {"Split":0.1263}, "6": {"Split":0.2013}, "7": {"Split":-0.0530}, "8": {"Split":-0.2318}, "9": {"Split":-0.4366}, "10": {"Split":-0.5535}, "A": {"Split":-0.4824} },
    "4,4": { "2": {"Split":-0.1923}, "3": {"Split":-0.1087}, "4": {"Split":-0.0204}, "5": {"Split":0.0819}, "6": {"Split":0.1514}, "7": {"Split":-0.1665}, "8": {"Split":-0.3261}, "9": {"Split":-0.5112}, "10": {"Split":-0.6250}, "A": {"Split":-0.5602} },
    "5,5": { "2": {"Split":-0.2902}, "3": {"Split":-0.2087}, "4": {"Split":-0.1193}, "5": {"Split":-0.0192}, "6": {"Split":0.0454}, "7": {"Split":-0.2939}, "8": {"Split":-0.4542}, "9": {"Split":-0.6341}, "10": {"Split":-0.7300}, "A": {"Split":-0.6688} },
    "6,6": { "2": {"Split":-0.2126}, "3": {"Split":-0.1197}, "4": {"Split":-0.0213}, "5": {"Split":0.0809}, "6": {"Split":0.1537}, "7": {"Split":-0.2644}, "8": {"Split":-0.4251}, "9": {"Split":-0.6106}, "10": {"Split":-0.7161}, "A": {"Split":-0.6534} },
    "7,7": { "2": {"Split":-0.1315}, "3": {"Split":-0.0437}, "4": {"Split":0.0493}, "5": {"Split":0.1467}, "6": {"Split":0.2474}, "7": {"Split":-0.0501}, "8": {"Split":-0.3920}, "9": {"Split":-0.5776}, "10": {"Split":-0.6573}, "A": {"Split":-0.6516} },
    "8,8": { "2": {"Split":0.0739}, "3": {"Split":0.1462}, "4": {"Split":0.2208}, "5": {"Split":0.2975}, "6": {"Split":0.4093}, "7": {"Split":0.3210}, "8": {"Split":-0.0227}, "9": {"Split":-0.3872}, "10": {"Split":-0.4807}, "A": {"Split":-0.3725} },
    "9,9": { "2": {"Split":0.1956}, "3": {"Split":0.2585}, "4": {"Split":0.3235}, "5": {"Split":0.3920}, "6": {"Split":0.4713}, "7": {"Split":0.3648}, "8": {"Split":0.2344}, "9": {"Split":-0.0780}, "10": {"Split":-0.3173}, "A": {"Split":-0.1368} },
    "10,10": { "2": {"Split":0.1348}, "3": {"Split":0.2128}, "4": {"Split":0.2934}, "5": {"Split":0.3804}, "6": {"Split":0.4681}, "7": {"Split":0.2966}, "8": {"Split":0.0644}, "9": {"Split":-0.2067}, "10": {"Split":-0.3713}, "A": {"Split":-0.2495} },
    "A,A": { "2": {"Split":0.4706}, "3": {"Split":0.5178}, "4": {"Split":0.5660}, "5": {"Split":0.6147}, "6": {"Split":0.6674}, "7": {"Split":0.4629}, "8": {"Split":0.3507}, "9": {"Split":0.2278}, "10": {"Split":0.1797}, "A": {"Split":0.1091} }
  },
  "surrenderNote": "Late Surrender EV is always -0.50 for any valid surrender hand"
}
